nagii
