Metadata-Version: 1.0
Name: nagii
Version: 0.1.3
Summary: A straightforward Nagios modelling library
Home-page: https://github.com/thekad/nagii
Author: Jorge Gallegos
Author-email: kad@blegh.net
License: MIT
Keywords: nagios
Platform: UNKNOWN
Classifier: Development Status :: 3 - Alpha
Classifier: Intended Audience :: System Administrators
Classifier: License :: OSI Approved :: MIT License
Classifier: Operating System :: OS Independent
Classifier: Programming Language :: Python :: 2.4
Classifier: Topic :: Software Development :: Libraries
Classifier: Topic :: System :: Monitoring
